enterest/__init__.py
enterest/enter_builtin_types.py
enterest/enter_builtins.py
enterest/interpreter.py
enterest/objects.py
enterest/scope.py
enterest/shell.py
enterest-0.0.dist-info/LICENSE.txt
enterest-0.0.dist-info/METADATA
enterest-0.0.dist-info/WHEEL
enterest-0.0.dist-info/entry_points.txt
enterest-0.0.dist-info/top_level.txt
enterest-0.0.dist-info/RECORD
