Metadata-Version: 2.1
Name: enterest
Version: 0.0
Summary: Enterest interpreter in Python.
Home-page: https://github.com/entitypengin
Author: entitypengin
Author-email: avagubot@gmail.com
Maintainer: entitypengin
Maintainer-email: avagubot@gmail.com
License: MIT
Classifier: Programming Language :: Python :: 3
Classifier: Programming Language :: Python :: 3.11
Classifier: License :: OSI Approved :: MIT License
License-File: LICENSE.txt
Requires-Dist: lark-parser
